Metadata-Version: 1.1
Name: barcode
Version: 0.6.0
Summary: Design NGS barcodes.
Home-page: https://git.lumc.nl/j.f.j.laros/barcode
Author: LUMC, Jeroen F.J. Laros
Author-email: J.F.J.Laros@lumc.nl
License: MIT License
Keywords: bioinformatics
Platform: any
Classifier: Development Status :: 3 - Alpha
Classifier: Intended Audience :: Science/Research
Classifier: Intended Audience :: Developers
Classifier: Operating System :: OS Independent
Classifier: Programming Language :: Python
Classifier: Topic :: Scientific/Engineering
